mute/__init__.py
mute/constants.py
mute/propagation.py
mute/surface.py
mute/underground.py
mute-3.0.0.dist-info/licenses/LICENSE
mute-3.0.0.dist-info/METADATA
mute-3.0.0.dist-info/WHEEL
mute-3.0.0.dist-info/top_level.txt
mute-3.0.0.dist-info/RECORD
