Metadata-Version: 2.4
Name: mute
Version: 3.0.0
Summary: Muon Intensity Code
Author-email: William Woodley <wwoodley@ualberta.ca>
License-Expression: BSD-3-Clause
Project-URL: Changelog, https://github.com/wjwoodley/mute/blob/main/CHANGELOG.md
Project-URL: Documentation, https://github.com/wjwoodley/mute/blob/main/docs/Tutorial.md
Project-URL: Homepage, https://github.com/wjwoodley/mute
Project-URL: Issues, https://github.com/wjwoodley/mute/issues
Classifier: Programming Language :: Python
Classifier: Programming Language :: Python :: 3
Classifier: Operating System :: OS Independent
Classifier: Topic :: Scientific/Engineering :: Physics
Classifier: Intended Audience :: Science/Research
License-File: LICENSE
Requires-Dist: mceq>=1.3
Requires-Dist: daemonflux
Requires-Dist: numpy
Requires-Dist: requests
Requires-Dist: scipy
Requires-Dist: tqdm
Dynamic: license-file
